fasttask/__init__.py
fasttask/main.py
fasttask/modules/__init__.py
fasttask/modules/board.py
fasttask/modules/clicontroller.py
fasttask/modules/cmd_example.py
fasttask/modules/command.py
fasttask/modules/dbhandler.py
fasttask/modules/task.py
test/__init__.py
test/test_board.py
test/test_task.py
fasttask-1.0.1.dist-info/LICENSE
fasttask-1.0.1.dist-info/METADATA
fasttask-1.0.1.dist-info/WHEEL
fasttask-1.0.1.dist-info/entry_points.txt
fasttask-1.0.1.dist-info/top_level.txt
fasttask-1.0.1.dist-info/RECORD
