Metadata-Version: 2.1
Name: fasttask
Version: 1.0.1
Summary: TODO
Home-page: https://github.com/LucasStarlingdePaulaSalles/fasttask
Author: Lucas Starling
Author-email: lucastarling1@gmail.com
Classifier: Programming Language :: Python :: 3
Classifier: License :: OSI Approved :: MIT License
Classifier: Operating System :: OS Independent
License-File: LICENSE
